LD_QQ_Method
