Metadata-Version: 2.1
Name: LD-QQ-Method
Version: 0.1.1
Summary: LD_QQ_Method
Home-page:  
Author: 忆古陌烟
Author-email: 3194775246@qq.com
License: MIT
Platform: UNKNOWN
Classifier: License :: OSI Approved :: MIT License
Classifier: Programming Language :: Python
Classifier: Programming Language :: Python :: 3
Classifier: Programming Language :: Python :: 3.6
Classifier: Programming Language :: Python :: Implementation :: CPython
Classifier: Programming Language :: Python :: Implementation :: PyPy
Requires-Python: >=3.6.0
License-File: LICENSE
